{
	"name": "forsink_copydata_forazurblob",
	"properties": {
		"linkedServiceName": {
			"referenceName": "copydata_inAzureblob_services",
			"type": "LinkedServiceReference"
		},
		"annotations": [],
		"type": "DelimitedText",
		"typeProperties": {
			"location": {
				"type": "AzureBlobStorageLocation",
				"folderPath": "archive",
				"container": "inbound"
			},
			"columnDelimiter": "|",
			"escapeChar": "\\",
			"firstRowAsHeader": true,
			"quoteChar": "\""
		},
		"schema": []
	},
	"type": "Microsoft.DataFactory/factories/datasets"
}